tests/__init__.py
tests/generate_large_graph.py
tests/test_converter.py
tests/test_data_loader.py
tests/test_legacy_renderer.py
tests/test_main.py
tests/test_renderer.py
venv/bin/rst2html.py
venv/bin/rst2html4.py
venv/bin/rst2html5.py
venv/bin/rst2latex.py
venv/bin/rst2man.py
venv/bin/rst2odt.py
venv/bin/rst2odt_prepstyles.py
venv/bin/rst2pseudoxml.py
venv/bin/rst2s5.py
venv/bin/rst2xetex.py
venv/bin/rst2xml.py
venv/bin/rstpep2html.py
yaml2dot/__init__.py
yaml2dot/__main__.py
yaml2dot/converter.py
yaml2dot/data_loader.py
yaml2dot/legacy_renderer.py
yaml2dot/renderer.py
yaml2dot-2.1.1.dist-info/LICENSE
yaml2dot-2.1.1.dist-info/METADATA
yaml2dot-2.1.1.dist-info/WHEEL
yaml2dot-2.1.1.dist-info/entry_points.txt
yaml2dot-2.1.1.dist-info/top_level.txt
yaml2dot-2.1.1.dist-info/RECORD
