Metadata-Version: 2.1
Name: yaml2dot
Version: 2.1.1
Summary: Python Yaml to Dot Converter
Author-email: Adrian Martinez <afmartinez1215@gmail.com>
Project-URL: Homepage, https://github.com/AdrianMartinezCodes/pythonYaml2Dot
Project-URL: Repository, https://github.com/AdrianMartinezCodes/pythonYaml2Dot.git
Classifier: Programming Language :: Python :: 3.8
Classifier: Programming Language :: Python :: 3.9
Classifier: Programming Language :: Python :: 3.10
Classifier: Programming Language :: Python :: 3.11
Classifier: License :: OSI Approved :: MIT License
Classifier: Operating System :: OS Independent
Requires-Python: >=3.8
License-File: LICENSE
Requires-Dist: PyYAML
Requires-Dist: networkx
Requires-Dist: click
Requires-Dist: pydot
Provides-Extra: all
Requires-Dist: yaml2dot[dev,test] ; extra == 'all'
Provides-Extra: dev
Requires-Dist: mypy ; extra == 'dev'
Requires-Dist: flake8 ; extra == 'dev'
Requires-Dist: yapf ; extra == 'dev'
Requires-Dist: isort ; extra == 'dev'
Provides-Extra: test
Requires-Dist: pytest ; extra == 'test'
Requires-Dist: coverage ; extra == 'test'
Requires-Dist: networkx ; extra == 'test'
